cwinsdk/__init__.py
cwinsdk/ntdll.py
cwinsdk/py.typed
cwinsdk/windows.py
cwinsdk/wintypes.py
cwinsdk/km/__init__.py
cwinsdk/km/ata.py
cwinsdk/km/dderror.py
cwinsdk/km/ntddk.py
cwinsdk/km/ntifs.py
cwinsdk/km/wdm.py
cwinsdk/km/crt/__init__.py
cwinsdk/km/crt/excpt.py
cwinsdk/shared/__init__.py
cwinsdk/shared/basetsd.py
cwinsdk/shared/devioctl.py
cwinsdk/shared/devpkey.py
cwinsdk/shared/devpropdef.py
cwinsdk/shared/diskguid.py
cwinsdk/shared/ehstorioctl.py
cwinsdk/shared/guiddef.py
cwinsdk/shared/minwindef.py
cwinsdk/shared/ntdddisk.py
cwinsdk/shared/ntddscsi.py
cwinsdk/shared/ntddstor.py
cwinsdk/shared/ntdef.py
cwinsdk/shared/ntstatus.py
cwinsdk/shared/nvme.py
cwinsdk/shared/scsi.py
cwinsdk/shared/secext.py
cwinsdk/shared/srb.py
cwinsdk/shared/windef.py
cwinsdk/shared/winerror.py
cwinsdk/shared/wtypesbase.py
cwinsdk/um/__init__.py
cwinsdk/um/audiosessiontypes.py
cwinsdk/um/combaseapi.py
cwinsdk/um/consoleapi.py
cwinsdk/um/consoleapi2.py
cwinsdk/um/fileapi.py
cwinsdk/um/handleapi.py
cwinsdk/um/ioapiset.py
cwinsdk/um/knownfolders.py
cwinsdk/um/libloaderapi.py
cwinsdk/um/lsalookup.py
cwinsdk/um/memoryapi.py
cwinsdk/um/minwinbase.py
cwinsdk/um/ntsecapi.py
cwinsdk/um/processenv.py
cwinsdk/um/processthreadsapi.py
cwinsdk/um/reason.py
cwinsdk/um/securitybaseapi.py
cwinsdk/um/setupapi.py
cwinsdk/um/shlobj_core.py
cwinsdk/um/shtypes.py
cwinsdk/um/synchapi.py
cwinsdk/um/sysinfoapi.py
cwinsdk/um/unknwn.py
cwinsdk/um/winbase.py
cwinsdk/um/wincontypes.py
cwinsdk/um/wingdi.py
cwinsdk/um/winioctl.py
cwinsdk/um/winnt.py
cwinsdk/um/winternl.py
cwinsdk/um/winuser.py
ctypes_windows_sdk-0.0.16.dist-info/licenses/LICENSE
ctypes_windows_sdk-0.0.16.dist-info/WHEEL
ctypes_windows_sdk-0.0.16.dist-info/METADATA
ctypes_windows_sdk-0.0.16.dist-info/RECORD
