Metadata-Version: 2.4
Name: ctypes-windows-sdk
Version: 0.0.16
Summary: Ctypes port of Windows SDK
Author-email: Dobatymo <Dobatymo@users.noreply.github.com>
Requires-Python: >=3.7
Classifier: Development Status :: 3 - Alpha
Classifier: Intended Audience :: Developers
Classifier: License :: OSI Approved :: ISC License (ISCL)
Classifier: Operating System :: Microsoft :: Windows
Classifier: Programming Language :: Python :: 3 :: Only
Classifier: Programming Language :: Python :: 3.7
Classifier: Programming Language :: Python :: 3.8
Classifier: Programming Language :: Python :: 3.9
Classifier: Programming Language :: Python :: 3.10
Classifier: Programming Language :: Python :: 3.11
Classifier: Programming Language :: Python :: 3.12
Classifier: Topic :: Software Development
Classifier: Topic :: System :: Operating System
License-File: LICENSE
Project-URL: Homepage, https://github.com/Dobatymo/ctypes-windows-sdk
